<?xml version="1.0" encoding="UTF-8"?>
<!DOCTYPE QtCreatorProfiles>
<!-- Written by QtCreator 3.5.1, 2015-10-25T23:02:02. -->
<qtcreator>
 <data>
  <variable>Profile.0</variable>
  <valuemap type="QVariantMap">
   <value type="bool" key="PE.Profile.AutoDetected">false</value>
   <value type="QString" key="PE.Profile.AutoDetectionSource"></value>
   <valuemap type="QVariantMap" key="PE.Profile.Data">
    <value type="QString" key="Android.GdbServer.Information"></value>
    <value type="QString" key="CMakeProjectManager.CMakeKitInformation">{0cfab314-c689-47c4-b591-c0d54916f3df}</value>
    <value type="QString" key="Debugger.Information">{3a82627b-37c0-45ec-9dbd-dea1b292b41f}</value>
    <value type="QString" key="PE.Profile.Device">Desktop Device</value>
    <value type="QByteArray" key="PE.Profile.DeviceType">Desktop</value>
    <valuelist type="QVariantList" key="PE.Profile.Environment"/>
    <value type="QString" key="PE.Profile.SysRoot"></value>
    <value type="QString" key="PE.Profile.ToolChain">ProjectExplorer.ToolChain.Gcc:{41200a83-06dc-4410-a63e-ad6e87d00023}</value>
    <valuemap type="QVariantMap" key="QbsProjectManager.qbs-properties"/>
    <value type="QString" key="QtPM4.mkSpecInformation"></value>
    <value type="int" key="QtSupport.QtInformation">2</value>
   </valuemap>
   <value type="QString" key="PE.Profile.Icon">:///DESKTOP///</value>
   <value type="QString" key="PE.Profile.Id">{4c7d2a6b-e6fb-4a75-add0-738d6c7e635c}</value>
   <valuelist type="QVariantList" key="PE.Profile.MutableInfo"/>
   <value type="QString" key="PE.Profile.Name">Desktop</value>
   <value type="bool" key="PE.Profile.SDK">false</value>
   <valuelist type="QVariantList" key="PE.Profile.StickyInfo"/>
  </valuemap>
 </data>
 <data>
  <variable>Profile.Count</variable>
  <value type="int">1</value>
 </data>
 <data>
  <variable>Profile.Default</variable>
  <value type="QString">{4c7d2a6b-e6fb-4a75-add0-738d6c7e635c}</value>
 </data>
 <data>
  <variable>Version</variable>
  <value type="int">1</value>
 </data>
</qtcreator>
