<?xml version="1.0" encoding="UTF-8"?>
<!DOCTYPE QtCreatorQtVersions>
<!-- Written by QtCreator 3.5.1, 2015-10-23T12:18:56. -->
<qtcreator>
 <data>
  <variable>QtVersion.0</variable>
  <valuemap type="QVariantMap">
   <value type="int" key="Id">2</value>
   <value type="QString" key="Name">Qt 5.3.1 in PATH (lib)</value>
   <value type="QString" key="QMakePath">/usr/lib/qt/bin/qmake</value>
   <value type="QString" key="QtVersion.Type">Qt4ProjectManager.QtVersion.Desktop</value>
   <value type="bool" key="isAutodetected">false</value>
  </valuemap>
 </data>
 <data>
  <variable>Version</variable>
  <value type="int">1</value>
 </data>
</qtcreator>
